pyniexp/__init__.py
pyniexp/_version.py
pyniexp/kbutils/__init__.py
pyniexp/kbutils/kbutils.py
pyniexp/mlplugins/__init__.py
pyniexp/mlplugins/mlplugins.py
pyniexp/network/__init__.py
pyniexp/network/connection.py
pyniexp/scanner/__init__.py
pyniexp/scanner/scannersynch.py
pyniexp/scanner/triggers.py
pyniexp/stimulator/__init__.py
pyniexp/stimulator/stimulation.py
pyniexp/stimulator/stimulatordlg.py
pyniexp/stimulator/stimulatordlg.ui
pyniexp/utils/__init__.py
pyniexp/utils/utils.py
PyNIExp-0.28.post3.dist-info/LICENSE
PyNIExp-0.28.post3.dist-info/METADATA
PyNIExp-0.28.post3.dist-info/WHEEL
PyNIExp-0.28.post3.dist-info/top_level.txt
PyNIExp-0.28.post3.dist-info/RECORD
