Metadata-Version: 2.1
Name: PyNIExp
Version: 0.28.post3
Summary: Python interface for NeuroImaging Experiments
Author-email: Tibor Auer <tibor.auer@gmail.com>
License: MIT License
Project-URL: Source, https://github.com/tiborauer/pyniexp
Project-URL: Tracker, https://github.com/tiborauer/pyniexp/issues
Keywords: neuroimaging,neurostimulation
Requires-Python: >=3.10
License-File: LICENSE
Requires-Dist: setuptools
Requires-Dist: pytest
Requires-Dist: pytest-cov
Requires-Dist: keyboard
Requires-Dist: nidaqmx
Requires-Dist: matplotlib
Requires-Dist: pyserial
Requires-Dist: pyqt6
Requires-Dist: pyqtgraph
